nestily/__init__.py
nestily-0.0.4.dist-info/LICENSE
nestily-0.0.4.dist-info/METADATA
nestily-0.0.4.dist-info/WHEEL
nestily-0.0.4.dist-info/top_level.txt
nestily-0.0.4.dist-info/RECORD
