Metadata-Version: 2.1
Name: nestily
Version: 0.0.4
Summary: Nested ish for python
Home-page: https://github.com/spencerbard/nestily
Author: Spencer Bard
Author-email: sbard26@gmail.com
License: UNKNOWN
Platform: UNKNOWN
Classifier: Programming Language :: Python :: 3
Classifier: License :: OSI Approved :: MIT License
Classifier: Operating System :: OS Independent
Requires-Python: >=3.6
